LICENSE.txt
MANIFEST.in
README.rst
setup.py
version
src/staticargs/__init__.py
src/staticargs.egg-info/PKG-INFO
src/staticargs.egg-info/SOURCES.txt
src/staticargs.egg-info/dependency_links.txt
src/staticargs.egg-info/top_level.txt