Metadata-Version: 1.0
Name: staticargs
Version: 1.0.0rc3
Summary: Work around mutable default arguments in function definitions
Home-page: https://github.com/HurricaneLabs/staticargs
Author: Colton Leekley-Winslow
Author-email: colton@hurricanelabs.com
License: UNKNOWN
Platform: UNKNOWN
